ApexTrackerPy/APEXAPI.py
ApexTrackerPy/ApexTRN.py
ApexTrackerPy/Apexclass.py
ApexTrackerPy/__init__.py
ApexTrackerPy/get_requests.py
ApexTrackerPy/lang.py
ApexTrackerPy/lang_data/__init__.py
ApexTrackerPy/lang_data/ja-JP.json
ApexTrackerPy-1.8.3.dist-info/LICENSE
ApexTrackerPy-1.8.3.dist-info/METADATA
ApexTrackerPy-1.8.3.dist-info/WHEEL
ApexTrackerPy-1.8.3.dist-info/top_level.txt
ApexTrackerPy-1.8.3.dist-info/RECORD
