Metadata-Version: 2.1
Name: ApexTrackerPy
Version: 1.8.3
Summary: Library for easily calling Apex tracker APIs (supports TRN and APEX LEGENDS APIs)
Home-page: https://github.com/nerrog/ApexTrackerPy
Author: nerrog
License: UNKNOWN
Platform: UNKNOWN
License-File: LICENSE
Requires-Dist: requests
